pinger_demo/Makefile
pinger_demo/README.rst
pinger_demo/__init__.py
pinger_demo/pinger_demo.py
pinger_demo/requirements.txt
pinger_demo-0.1.0.dist-info/LICENSE.txt
pinger_demo-0.1.0.dist-info/WHEEL
pinger_demo-0.1.0.dist-info/METADATA
pinger_demo-0.1.0.dist-info/RECORD
