Metadata-Version: 2.1
Name: pinger-demo
Version: 0.1.0
Summary: 
Author: Alex Duki
Author-email: aleksey.duki.ext@nokia.com
Classifier: Programming Language :: Python :: 2
Classifier: Programming Language :: Python :: 2.7
Classifier: Programming Language :: Python :: 3
Classifier: Programming Language :: Python :: 3.4
Classifier: Programming Language :: Python :: 3.5
Classifier: Programming Language :: Python :: 3.6
Classifier: Programming Language :: Python :: 3.7
Classifier: Programming Language :: Python :: 3.8
Classifier: Programming Language :: Python :: 3.9
Requires-Dist: Pillow (>=8.0,<9.0); python_version >= "3.6"
Requires-Dist: pystray (==0.17.2)
Requires-Dist: python-xlib (==0.29)
Requires-Dist: six (==1.15.0)
